<?xml version="1.0" encoding="utf-8" ?>
<Advertisements>
  <Ad>
    <ImageUrl>image/img1.png</ImageUrl>
    <NavigateUrl>https://google.com</NavigateUrl>
    <AlternateText>Advetisement</AlternateText>
    <Impression>100</Impression>
    <Keyword>Banner</Keyword>
  </Ad>
  <Ad>
    <ImageUrl>image/img2.png</ImageUrl>
    <NavigateUrl>https://google.com</NavigateUrl>
    <AlternateText>Advetisement</AlternateText>
    <Impression>100</Impression>
    <Keyword>Banner</Keyword>
  </Ad>
  <Ad>
    <ImageUrl>image/img3.png</ImageUrl>
    <NavigateUrl>https://google.com</NavigateUrl>
    <AlternateText>Advetisement</AlternateText>
    <Impression>100</Impression>
    <Keyword>Banner</Keyword>
  </Ad>
</Advertisements>